itkwasm_htj2k/__init__.py
itkwasm_htj2k/_version.py
itkwasm_htj2k/decode.py
itkwasm_htj2k/decode_async.py
itkwasm_htj2k/encode.py
itkwasm_htj2k/encode_async.py
itkwasm_htj2k-2.3.1.dist-info/METADATA
itkwasm_htj2k-2.3.1.dist-info/WHEEL
itkwasm_htj2k-2.3.1.dist-info/RECORD
